{
  "name": "system-health-monitor",
  "version": "1.1.1",
  "description": "8层系统监控集成，提供健康评分、安全报告和性能分析（通用版）",
  "author": "ZLMbot 🦞",
  "tags": ["monitoring", "security", "health", "system"],
  "license": "MIT",
  "homepage": "https://github.com/openclaw/openclaw",
  "repository": {
    "type": "git",
    "url": "https://github.com/openclaw/openclaw"
  },
  "requirements": {
    "openclaw": ">=0.1.0",
    "os": "linux",
    "dependencies": ["systemd", "jq"]
  },
  "entry": "SKILL.md",
  "main": "scripts/health-check.sh"
}
